code_diff/__init__.py
code_diff/ast_mapper.py
code_diff/cli.py
code_diff/diff_parser.py
code_diff/git.py
code_diff/languages.py
code_diff/output.py
code_diff_ast-0.1.0.dist-info/METADATA
code_diff_ast-0.1.0.dist-info/WHEEL
code_diff_ast-0.1.0.dist-info/entry_points.txt
code_diff_ast-0.1.0.dist-info/RECORD
