Metadata-Version: 2.4
Name: code-diff-ast
Version: 0.1.0
Summary: Git diff to AST mapper CLI for LLM consumption
Requires-Python: >=3.10
Requires-Dist: click>=8.0
Requires-Dist: tree-sitter-go>=0.21.0
Requires-Dist: tree-sitter-javascript>=0.21.0
Requires-Dist: tree-sitter-python>=0.21.0
Requires-Dist: tree-sitter-rust>=0.21.0
Requires-Dist: tree-sitter-typescript>=0.21.0
Requires-Dist: tree-sitter>=0.21.0
Requires-Dist: unidiff>=0.7.0
